arcade_curtains/__init__.py
arcade_curtains/animation.py
arcade_curtains/event.py
arcade_curtains/helpers.py
arcade_curtains/scene.py
arcade_curtains-0.4.1.dist-info/AUTHORS
arcade_curtains-0.4.1.dist-info/LICENSE
arcade_curtains-0.4.1.dist-info/METADATA
arcade_curtains-0.4.1.dist-info/WHEEL
arcade_curtains-0.4.1.dist-info/pbr.json
arcade_curtains-0.4.1.dist-info/top_level.txt
arcade_curtains-0.4.1.dist-info/RECORD
