Metadata-Version: 2.1
Name: arcade-curtains
Version: 0.4.1
Summary: A scene and event manager for python arcade
Home-page: https://github.com/maarten-dp/arcade-curtains
Author: Maarten De Paepe
Author-email: "maarten.de.paepe@gmail.com"
License: UNKNOWN
Platform: UNKNOWN
Classifier: Development Status :: 4 - Beta
Classifier: Operating System :: MacOS :: MacOS X
Classifier: Operating System :: Microsoft :: Windows
Classifier: Operating System :: POSIX
Classifier: License :: OSI Approved :: MIT License
Classifier: Programming Language :: Python
Classifier: Programming Language :: Python :: 3.6
Requires-Dist: arcade
Requires-Dist: pbr (>=3.0)
Requires-Dist: scipy
